odoo/addons/web_field_required_invisible_manager/README.rst
odoo/addons/web_field_required_invisible_manager/__init__.py
odoo/addons/web_field_required_invisible_manager/__manifest__.py
odoo/addons/web_field_required_invisible_manager/i18n/it.po
odoo/addons/web_field_required_invisible_manager/i18n/web_field_required_invisible_manager.pot
odoo/addons/web_field_required_invisible_manager/models/__init__.py
odoo/addons/web_field_required_invisible_manager/models/base.py
odoo/addons/web_field_required_invisible_manager/models/custom_field_restriction.py
odoo/addons/web_field_required_invisible_manager/models/ir_model.py
odoo/addons/web_field_required_invisible_manager/models/ir_ui_view.py
odoo/addons/web_field_required_invisible_manager/readme/CONTRIBUTORS.rst
odoo/addons/web_field_required_invisible_manager/readme/DESCRIPTION.rst
odoo/addons/web_field_required_invisible_manager/readme/ROADMAP.rst
odoo/addons/web_field_required_invisible_manager/readme/USAGE.rst
odoo/addons/web_field_required_invisible_manager/security/ir.model.access.csv
odoo/addons/web_field_required_invisible_manager/static/description/icon.png
odoo/addons/web_field_required_invisible_manager/static/description/index.html
odoo/addons/web_field_required_invisible_manager/tests/__init__.py
odoo/addons/web_field_required_invisible_manager/tests/test_web_field_required_invisible_manager.py
odoo/addons/web_field_required_invisible_manager/views/views.xml
odoo14_addon_web_field_required_invisible_manager-14.0.2.4.0.dist-info/METADATA
odoo14_addon_web_field_required_invisible_manager-14.0.2.4.0.dist-info/WHEEL
odoo14_addon_web_field_required_invisible_manager-14.0.2.4.0.dist-info/top_level.txt
odoo14_addon_web_field_required_invisible_manager-14.0.2.4.0.dist-info/RECORD
