Metadata-Version: 2.1
Name: odoo14-addon-web_field_required_invisible_manager
Version: 14.0.2.4.0
Summary: Web Field Required Invisible Readonly Managerr
Home-page: https://github.com/OCA/web
Author: Ilyas, ooops404, Odoo Community Association (OCA)
Author-email: support@odoo-community.org
License: AGPL-3
Classifier: Programming Language :: Python
Classifier: Framework :: Odoo
Classifier: Framework :: Odoo :: 14.0
Classifier: License :: OSI Approved :: GNU Affero General Public License v3
Requires-Python: >=3.6
Requires-Dist: odoo<14.1dev,>=14.0a
